[
  {
    "provider": "AWS",
    "instance": "t3.micro",
    "cpu": 2,
    "ram": 1,
    "storage": 20,
    "region": "us-east-1",
    "price_inr_per_hour": 1.75,
    "performance_score": 68,
    "reliability_score": 99.95
  },
  {
    "provider": "AWS",
    "instance": "t3.small",
    "cpu": 2,
    "ram": 2,
    "storage": 30,
    "region": "us-east-1",
    "price_inr_per_hour": 3.10,
    "performance_score": 72,
    "reliability_score": 99.95
  },
  {
    "provider": "AWS",
    "instance": "t3.medium",
    "cpu": 2,
    "ram": 4,
    "storage": 50,
    "region": "us-east-1",
    "price_inr_per_hour": 6.20,
    "performance_score": 78,
    "reliability_score": 99.99
  },
  {
    "provider": "AWS",
    "instance": "t3.large",
    "cpu": 2,
    "ram": 8,
    "storage": 80,
    "region": "us-east-1",
    "price_inr_per_hour": 12.40,
    "performance_score": 82,
    "reliability_score": 99.99
  },
  {
    "provider": "AWS",
    "instance": "t3.xlarge",
    "cpu": 4,
    "ram": 16,
    "storage": 100,
    "region": "us-east-1",
    "price_inr_per_hour": 24.80,
    "performance_score": 88,
    "reliability_score": 99.99
  },
  {
    "provider": "AWS",
    "instance": "t3.micro",
    "cpu": 2,
    "ram": 1,
    "storage": 20,
    "region": "ap-south-1",
    "price_inr_per_hour": 1.55,
    "performance_score": 67,
    "reliability_score": 99.90
  },
  {
    "provider": "AWS",
    "instance": "t3.small",
    "cpu": 2,
    "ram": 2,
    "storage": 30,
    "region": "ap-south-1",
    "price_inr_per_hour": 2.80,
    "performance_score": 71,
    "reliability_score": 99.90
  },
  {
    "provider": "AWS",
    "instance": "t3.medium",
    "cpu": 2,
    "ram": 4,
    "storage": 50,
    "region": "ap-south-1",
    "price_inr_per_hour": 5.60,
    "performance_score": 76,
    "reliability_score": 99.95
  },
  {
    "provider": "AWS",
    "instance": "t3.large",
    "cpu": 2,
    "ram": 8,
    "storage": 80,
    "region": "ap-south-1",
    "price_inr_per_hour": 11.20,
    "performance_score": 80,
    "reliability_score": 99.95
  },
  {
    "provider": "AWS",
    "instance": "t3.xlarge",
    "cpu": 4,
    "ram": 16,
    "storage": 100,
    "region": "ap-south-1",
    "price_inr_per_hour": 22.40,
    "performance_score": 86,
    "reliability_score": 99.95
  },
  {
    "provider": "AWS",
    "instance": "m5.large",
    "cpu": 2,
    "ram": 8,
    "storage": 100,
    "region": "ap-south-1",
    "price_inr_per_hour": 14.30,
    "performance_score": 85,
    "reliability_score": 99.99
  },
  {
    "provider": "AWS",
    "instance": "c5.large",
    "cpu": 2,
    "ram": 4,
    "storage": 50,
    "region": "ap-south-1",
    "price_inr_per_hour": 12.60,
    "performance_score": 92,
    "reliability_score": 99.99
  },
  {
    "provider": "AWS",
    "instance": "r5.large",
    "cpu": 2,
    "ram": 16,
    "storage": 100,
    "region": "ap-south-1",
    "price_inr_per_hour": 18.70,
    "performance_score": 83,
    "reliability_score": 99.99
  },
  {
    "provider": "AWS",
    "instance": "m5.xlarge",
    "cpu": 4,
    "ram": 16,
    "storage": 200,
    "region": "eu-west-1",
    "price_inr_per_hour": 28.50,
    "performance_score": 89,
    "reliability_score": 99.99
  },
  {
    "provider": "AWS",
    "instance": "c5.xlarge",
    "cpu": 4,
    "ram": 8,
    "storage": 100,
    "region": "eu-west-1",
    "price_inr_per_hour": 25.20,
    "performance_score": 93,
    "reliability_score": 99.99
  },
  {
    "provider": "Azure",
    "instance": "B1s",
    "cpu": 1,
    "ram": 1,
    "storage": 20,
    "region": "us-east-1",
    "price_inr_per_hour": 1.40,
    "performance_score": 60,
    "reliability_score": 99.90
  },
  {
    "provider": "Azure",
    "instance": "B2s",
    "cpu": 2,
    "ram": 4,
    "storage": 50,
    "region": "us-east-1",
    "price_inr_per_hour": 6.80,
    "performance_score": 74,
    "reliability_score": 99.95
  },
  {
    "provider": "Azure",
    "instance": "B4ms",
    "cpu": 4,
    "ram": 16,
    "storage": 100,
    "region": "us-east-1",
    "price_inr_per_hour": 24.50,
    "performance_score": 80,
    "reliability_score": 99.95
  },
  {
    "provider": "Azure",
    "instance": "D2s_v3",
    "cpu": 2,
    "ram": 8,
    "storage": 50,
    "region": "us-east-1",
    "price_inr_per_hour": 14.20,
    "performance_score": 84,
    "reliability_score": 99.99
  },
  {
    "provider": "Azure",
    "instance": "D4s_v3",
    "cpu": 4,
    "ram": 16,
    "storage": 100,
    "region": "us-east-1",
    "price_inr_per_hour": 28.40,
    "performance_score": 88,
    "reliability_score": 99.99
  },
  {
    "provider": "Azure",
    "instance": "B1s",
    "cpu": 1,
    "ram": 1,
    "storage": 20,
    "region": "ap-south-1",
    "price_inr_per_hour": 1.25,
    "performance_score": 58,
    "reliability_score": 99.85
  },
  {
    "provider": "Azure",
    "instance": "B2s",
    "cpu": 2,
    "ram": 4,
    "storage": 50,
    "region": "ap-south-1",
    "price_inr_per_hour": 6.10,
    "performance_score": 72,
    "reliability_score": 99.90
  },
  {
    "provider": "Azure",
    "instance": "B4ms",
    "cpu": 4,
    "ram": 16,
    "storage": 100,
    "region": "ap-south-1",
    "price_inr_per_hour": 22.00,
    "performance_score": 78,
    "reliability_score": 99.90
  },
  {
    "provider": "Azure",
    "instance": "D2s_v3",
    "cpu": 2,
    "ram": 8,
    "storage": 50,
    "region": "ap-south-1",
    "price_inr_per_hour": 12.80,
    "performance_score": 82,
    "reliability_score": 99.95
  },
  {
    "provider": "Azure",
    "instance": "D4s_v3",
    "cpu": 4,
    "ram": 16,
    "storage": 100,
    "region": "ap-south-1",
    "price_inr_per_hour": 25.60,
    "performance_score": 86,
    "reliability_score": 99.95
  },
  {
    "provider": "Azure",
    "instance": "F2s_v2",
    "cpu": 2,
    "ram": 4,
    "storage": 30,
    "region": "ap-south-1",
    "price_inr_per_hour": 12.10,
    "performance_score": 90,
    "reliability_score": 99.95
  },
  {
    "provider": "Azure",
    "instance": "E2s_v3",
    "cpu": 2,
    "ram": 16,
    "storage": 100,
    "region": "ap-south-1",
    "price_inr_per_hour": 18.90,
    "performance_score": 81,
    "reliability_score": 99.95
  },
  {
    "provider": "Azure",
    "instance": "D8s_v3",
    "cpu": 8,
    "ram": 32,
    "storage": 200,
    "region": "eu-west-1",
    "price_inr_per_hour": 58.00,
    "performance_score": 91,
    "reliability_score": 99.99
  },
  {
    "provider": "Azure",
    "instance": "F4s_v2",
    "cpu": 4,
    "ram": 8,
    "storage": 50,
    "region": "eu-west-1",
    "price_inr_per_hour": 24.80,
    "performance_score": 92,
    "reliability_score": 99.99
  },
  {
    "provider": "GCP",
    "instance": "e2-micro",
    "cpu": 2,
    "ram": 1,
    "storage": 20,
    "region": "us-east-1",
    "price_inr_per_hour": 1.30,
    "performance_score": 65,
    "reliability_score": 99.95
  },
  {
    "provider": "GCP",
    "instance": "e2-small",
    "cpu": 2,
    "ram": 2,
    "storage": 30,
    "region": "us-east-1",
    "price_inr_per_hour": 2.50,
    "performance_score": 70,
    "reliability_score": 99.95
  },
  {
    "provider": "GCP",
    "instance": "e2-medium",
    "cpu": 2,
    "ram": 4,
    "storage": 50,
    "region": "us-east-1",
    "price_inr_per_hour": 5.00,
    "performance_score": 77,
    "reliability_score": 99.99
  },
  {
    "provider": "GCP",
    "instance": "e2-standard-4",
    "cpu": 4,
    "ram": 16,
    "storage": 100,
    "region": "us-east-1",
    "price_inr_per_hour": 20.00,
    "performance_score": 85,
    "reliability_score": 99.99
  },
  {
    "provider": "GCP",
    "instance": "e2-standard-8",
    "cpu": 8,
    "ram": 32,
    "storage": 200,
    "region": "us-east-1",
    "price_inr_per_hour": 40.00,
    "performance_score": 90,
    "reliability_score": 99.99
  },
  {
    "provider": "GCP",
    "instance": "e2-micro",
    "cpu": 2,
    "ram": 1,
    "storage": 20,
    "region": "ap-south-1",
    "price_inr_per_hour": 1.15,
    "performance_score": 64,
    "reliability_score": 99.90
  },
  {
    "provider": "GCP",
    "instance": "e2-small",
    "cpu": 2,
    "ram": 2,
    "storage": 30,
    "region": "ap-south-1",
    "price_inr_per_hour": 2.25,
    "performance_score": 69,
    "reliability_score": 99.90
  },
  {
    "provider": "GCP",
    "instance": "e2-medium",
    "cpu": 2,
    "ram": 4,
    "storage": 50,
    "region": "ap-south-1",
    "price_inr_per_hour": 4.50,
    "performance_score": 75,
    "reliability_score": 99.95
  },
  {
    "provider": "GCP",
    "instance": "e2-standard-4",
    "cpu": 4,
    "ram": 16,
    "storage": 100,
    "region": "ap-south-1",
    "price_inr_per_hour": 18.00,
    "performance_score": 84,
    "reliability_score": 99.95
  },
  {
    "provider": "GCP",
    "instance": "e2-standard-8",
    "cpu": 8,
    "ram": 32,
    "storage": 200,
    "region": "ap-south-1",
    "price_inr_per_hour": 36.00,
    "performance_score": 89,
    "reliability_score": 99.95
  },
  {
    "provider": "GCP",
    "instance": "n2-standard-2",
    "cpu": 2,
    "ram": 8,
    "storage": 80,
    "region": "ap-south-1",
    "price_inr_per_hour": 13.50,
    "performance_score": 86,
    "reliability_score": 99.99
  },
  {
    "provider": "GCP",
    "instance": "c2-standard-4",
    "cpu": 4,
    "ram": 16,
    "storage": 100,
    "region": "ap-south-1",
    "price_inr_per_hour": 24.00,
    "performance_score": 94,
    "reliability_score": 99.99
  },
  {
    "provider": "GCP",
    "instance": "n2-standard-4",
    "cpu": 4,
    "ram": 16,
    "storage": 100,
    "region": "eu-west-1",
    "price_inr_per_hour": 26.50,
    "performance_score": 87,
    "reliability_score": 99.99
  },
  {
    "provider": "GCP",
    "instance": "c2-standard-8",
    "cpu": 8,
    "ram": 32,
    "storage": 200,
    "region": "eu-west-1",
    "price_inr_per_hour": 52.00,
    "performance_score": 95,
    "reliability_score": 99.99
  },
  {
    "provider": "AWS",
    "instance": "t3.medium",
    "cpu": 2,
    "ram": 4,
    "storage": 50,
    "region": "eu-west-1",
    "price_inr_per_hour": 6.80,
    "performance_score": 78,
    "reliability_score": 99.99
  },
  {
    "provider": "AWS",
    "instance": "t3.large",
    "cpu": 2,
    "ram": 8,
    "storage": 80,
    "region": "eu-west-1",
    "price_inr_per_hour": 13.60,
    "performance_score": 82,
    "reliability_score": 99.99
  }
]
